wild_blue_yonder/__init__.py
wild_blue_yonder/instructions/__init__.py
wild_blue_yonder/instructions/yes_no.yaml
wild_blue_yonder/iteractions/__init__.py
wild_blue_yonder/iteractions/like_good.py
wild_blue_yonder/lm/__init__.py
wild_blue_yonder/lm/lm_api.py
wild_blue_yonder/summaries/__init__.py
wild_blue_yonder/summaries/worth_attention.py
wild_blue_yonder/toolset/__init__.py
wild_blue_yonder/toolset/like.py
wild_blue_yonder-0.0.6.dist-info/LICENSE
wild_blue_yonder-0.0.6.dist-info/METADATA
wild_blue_yonder-0.0.6.dist-info/WHEEL
wild_blue_yonder-0.0.6.dist-info/top_level.txt
wild_blue_yonder-0.0.6.dist-info/RECORD
